examples/config_scanner_project/__init__.py
examples/dependency_checker_project/__init__.py
examples/permissions_checker_project/__init__.py
examples/secrets_scanner_project/__init__.py
examples/secrets_scanner_project/example.py
safeguard_toolkit/__init__.py
safeguard_toolkit/core/__init__.py
safeguard_toolkit/core/base_scanner.py
safeguard_toolkit/scanners/__init__.py
safeguard_toolkit/scanners/config_scanner.py
safeguard_toolkit/scanners/dependency_checker.py
safeguard_toolkit/scanners/permissions_checker.py
safeguard_toolkit/scanners/secrets_scanner.py
safeguard_toolkit/utils/__init__.py
safeguard_toolkit/utils/config_loader.py
safeguard_toolkit/utils/file_utils.py
safeguard_toolkit/utils/issue_tracker.py
safeguard_toolkit/utils/key_value_utils.py
safeguard_toolkit/utils/licences.py
safeguard_toolkit-0.1.5.dist-info/licenses/LICENSE
safeguard_toolkit-0.1.5.dist-info/METADATA
safeguard_toolkit-0.1.5.dist-info/WHEEL
safeguard_toolkit-0.1.5.dist-info/top_level.txt
safeguard_toolkit-0.1.5.dist-info/RECORD
