Metadata-Version: 2.4
Name: safeguard-toolkit
Version: 0.1.5
Summary: A toolkit for scanning configs, secrets, and permissions.
Author-email: Purvi Verma <20ce01050@iitbbs.ac.in>
License: MIT
Project-URL: Homepage, https://github.com/purvi1508/Safeguard
Requires-Python: >=3.12
License-File: LICENSE
Requires-Dist: pyyaml==6.0.2
Requires-Dist: requests==2.32.3
Requires-Dist: packaging==25.0
Requires-Dist: toml==0.10.2
Requires-Dist: packaging==25.0
Dynamic: license-file
